{
  "type": "Feature",
  "properties": {
    "gn:admin1_code":"01",
    "gn:asciiname":"Kayyah",
    "gn:country_code":"AE",
    "gn:dem":121,
    "gn:feature_class":"P",
    "gn:feature_code":"PPL",
    "gn:name":"Kayyah",
    "gn:population":0,
    "gn:timezone":"Asia/Dubai",
    "iso:country":"AE",
    "name:und_x_variant":[
        "Kayya",
        "Kayyah"
    ],
    "wof:name":"Kayyah",
    "wof:placetype":"locality"
},
  "geometry": {"coordinates":[53.68541,23.15696],"type":"Point"}
}