{
  "type": "Feature",
  "properties": {
    "gn:admin1_code":"06",
    "gn:asciiname":"Al Khan",
    "gn:country_code":"AE",
    "gn:dem":3,
    "gn:feature_class":"P",
    "gn:feature_code":"PPL",
    "gn:name":"Al Kh\u0101n",
    "gn:population":0,
    "gn:timezone":"Asia/Dubai",
    "iso:country":"AE",
    "name:ara_x_preferred":[
        "Al Kh\u0101n"
    ],
    "name:fas_x_preferred":[
        "\u0627\u0644\u062e\u0627\u0646"
    ],
    "name:nno_x_preferred":[
        "Al Khan"
    ],
    "name:pol_x_preferred":[
        "Al-Chan"
    ],
    "name:und_x_variant":[
        "Kh\u0101n"
    ],
    "name:urd_x_preferred":[
        "\u0627\u0644\u062e\u0627\u0646"
    ],
    "wof:name":"Al Khan",
    "wof:placetype":"neighbourhood"
},
  "geometry": {"coordinates":[55.35901,25.33141],"type":"Point"}
}