{
  "type": "Feature",
  "properties": {
    "gn:admin1_code":"01",
    "gn:asciiname":"Qattarah",
    "gn:country_code":"AE",
    "gn:dem":281,
    "gn:feature_class":"P",
    "gn:feature_code":"PPL",
    "gn:name":"Qa\u0163\u0163\u0101rah",
    "gn:population":0,
    "gn:timezone":"Asia/Dubai",
    "iso:country":"AE",
    "name:und_x_variant":[
        "Al-Qatarah",
        "Qatara",
        "Qa\u1e6d\u1e6d\u0101ra",
        "Qat\u0101rah",
        "Qa\u0163\u0163\u0101rah"
    ],
    "wof:lang_x_official":[
        "ara"
    ],
    "wof:lang_x_spoken":[
        "ara"
    ],
    "wof:name":"Qattarah",
    "wof:placetype":"neighbourhood"
},
  "geometry": {"coordinates":[55.75566,24.25993],"type":"Point"}
}