{
  "type": "Feature",
  "properties": {
    "gn:admin1_code":"04",
    "gn:asciiname":"Theeb",
    "gn:country_code":"AE",
    "gn:dem":27,
    "gn:feature_class":"P",
    "gn:feature_code":"PPL",
    "gn:name":"Theeb",
    "gn:population":0,
    "gn:timezone":"Asia/Dubai",
    "iso:country":"AE",
    "name:ara_x_preferred":[
        "\u0630\u064a\u0628"
    ],
    "name:cat_x_preferred":[
        "Theeb"
    ],
    "name:deu_x_preferred":[
        "Theeb"
    ],
    "name:fas_x_preferred":[
        "\u0630\u06cc\u0628"
    ],
    "name:fra_x_preferred":[
        "Theeb"
    ],
    "name:ind_x_preferred":[
        "Theeb"
    ],
    "name:ita_x_preferred":[
        "Theeb"
    ],
    "name:kor_x_preferred":[
        "\ub514\ube0c"
    ],
    "name:nld_x_preferred":[
        "Theeb"
    ],
    "name:por_x_preferred":[
        "Theeb"
    ],
    "name:rus_x_preferred":[
        "\u0413\u043e\u0440\u0434\u043e\u0441\u0442\u044c"
    ],
    "name:spa_x_preferred":[
        "Theeb"
    ],
    "name:tur_x_preferred":[
        "Theeb"
    ],
    "name:ukr_x_preferred":[
        "\u0422\u0456\u0431"
    ],
    "name:vie_x_preferred":[
        "Theeb"
    ],
    "name:zho_x_preferred":[
        "\u5e0c\u5e03"
    ],
    "wof:name":"Theeb",
    "wof:placetype":"neighbourhood"
},
  "geometry": {"coordinates":[56.34206,25.24501],"type":"Point"}
}