{
  "type": "Feature",
  "properties": {
    "gn:admin1_code":"04",
    "gn:asciiname":"Theeb",
    "gn:country_code":"AE",
    "gn:dem":27,
    "gn:feature_class":"P",
    "gn:feature_code":"PPL",
    "gn:name":"Theeb",
    "gn:population":0,
    "gn:timezone":"Asia/Dubai",
    "iso:country":"AE",
    "wof:name":"Theeb",
    "wof:placetype":"neighbourhood"
},
  "geometry": {"coordinates":[56.34206,25.24501],"type":"Point"}
}