{
  "type": "Feature",
  "properties": {
    "gn:admin1_code":"04",
    "gn:asciiname":"Rul Dadna",
    "gn:country_code":"AE",
    "gn:dem":8,
    "gn:feature_class":"P",
    "gn:feature_code":"PPL",
    "gn:name":"R\u016bl \u1e10adn\u0101",
    "gn:population":0,
    "gn:timezone":"Asia/Dubai",
    "iso:country":"AE",
    "name:und_x_variant":[
        "Rul Dhadna",
        "R\u016bl \u1e10adnah",
        "Rol \u1e0cadnah",
        "R\u016bl \u1e10adn\u0101"
    ],
    "wof:name":"Rul Dadna",
    "wof:placetype":"locality"
},
  "geometry": {"coordinates":[56.34546,25.55481],"type":"Point"}
}