{
  "type": "Feature",
  "properties": {
    "gn:admin1_code":"02",
    "gn:asciiname":"Sufayri",
    "gn:country_code":"AE",
    "gn:dem":315,
    "gn:feature_class":"P",
    "gn:feature_code":"PPL",
    "gn:name":"\u015eufayr\u012b",
    "gn:population":0,
    "gn:timezone":"Asia/Dubai",
    "iso:country":"AE",
    "name:und_x_variant":[
        "\u015eufayr\u012b"
    ],
    "wof:name":"Sufayri",
    "wof:placetype":"locality"
},
  "geometry": {"coordinates":[56.12647,24.81168],"type":"Point"}
}