{
  "type": "Feature",
  "properties": {
    "gn:admin1_code":"05",
    "gn:asciiname":"Ghaghah",
    "gn:cc2":"AE",
    "gn:country_code":"AE",
    "gn:dem":119,
    "gn:feature_class":"P",
    "gn:feature_code":"PPL",
    "gn:name":"Gh\u0101ghah",
    "gn:population":0,
    "gn:timezone":"Asia/Dubai",
    "iso:country":"AE",
    "name:ara_x_preferred":[
        "\u063a\u0627\u063a\u0627"
    ],
    "name:und_x_variant":[
        "Gargaha",
        "Gh\u0101ghah"
    ],
    "wof:name":"Ghaghah",
    "wof:placetype":"locality"
},
  "geometry": {"coordinates":[56.06667,25.76667],"type":"Point"}
}