{
  "type": "Feature",
  "properties": {
    "gn:admin1_code":"04",
    "gn:asciiname":"Al Kubus",
    "gn:country_code":"AE",
    "gn:dem":13,
    "gn:feature_class":"P",
    "gn:feature_code":"PPL",
    "gn:name":"Al Kub\u016bs",
    "gn:population":0,
    "gn:timezone":"Asia/Dubai",
    "iso:country":"AE",
    "name:ara_x_preferred":[
        "\u0627\u0644\u0643\u0628\u0633"
    ],
    "name:ara_x_variant":[
        "Al Kub\u016bs"
    ],
    "wof:name":"Al Kubus",
    "wof:placetype":"locality"
},
  "geometry": {"coordinates":[56.3047,25.60151],"type":"Point"}
}