{
  "type": "Feature",
  "properties": {
    "gn:admin1_code":"04",
    "gn:asciiname":"Tayyibah",
    "gn:country_code":"AE",
    "gn:dem":475,
    "gn:feature_class":"P",
    "gn:feature_code":"PPL",
    "gn:name":"\u0162ayyibah",
    "gn:population":0,
    "gn:timezone":"Asia/Dubai",
    "iso:country":"AE",
    "name:und_x_variant":[
        "Tayiban",
        "Tayyibah",
        "Taiyibah",
        "Tayibah",
        "\u0162ayyibah"
    ],
    "wof:name":"Tayyibah",
    "wof:placetype":"locality"
},
  "geometry": {"coordinates":[56.17075,25.41228],"type":"Point"}
}