{
  "type": "Feature",
  "properties": {
    "gn:admin1_code":"05",
    "gn:asciiname":"Al Usayli",
    "gn:country_code":"AE",
    "gn:dem":25,
    "gn:feature_class":"P",
    "gn:feature_code":"PPL",
    "gn:name":"Al Usayl\u012b",
    "gn:population":0,
    "gn:timezone":"Asia/Dubai",
    "iso:country":"AE",
    "name:ara_x_preferred":[
        "\u0627\u0644\u0639\u0633\u064a\u0644\u064a"
    ],
    "name:und_x_variant":[
        "Lisaili",
        "Al Usayl\u012b"
    ],
    "wof:name":"Al Usayli",
    "wof:placetype":"locality"
},
  "geometry": {"coordinates":[56.00814,25.62676],"type":"Point"}
}