{
  "type": "Feature",
  "properties": {
    "iso:country":"AE",
    "qs:gn_pop":0,
    "qs:name":"\u0643\u0648\u0631\u0646\u064a\u0634 \u0627\u0644\u0628\u062d\u064a\u0631\u0629",
    "qs:name_adm0":"\u0627\u0644\u0627\u0645\u0627\u0631\u0627\u062a",
    "qs:name_adm1":"\u0627\u0644\u0634\u0627\u0631\u0642\u0629",
    "qs:photos":101,
    "qs:photos_1k":20,
    "qs:photos_9k":1,
    "qs:photos_9r":3,
    "qs:photos_all":101,
    "qs:photos_sr":3,
    "qs:placetype":"Suburb",
    "qs:pop_sr":"0",
    "qs:woe_adm0":23424738,
    "wof:name":"\u0643\u0648\u0631\u0646\u064a\u0634 \u0627\u0644\u0628\u062d\u064a\u0631\u0629",
    "wof:placetype":"neighbourhood"
},
  "geometry": {"coordinates":[55.387833,25.3282],"type":"Point"}
}