{
  "type": "Feature",
  "properties": {
    "gn:admin1_code":"04",
    "gn:asciiname":"Riyamah",
    "gn:country_code":"AE",
    "gn:dem":161,
    "gn:feature_class":"P",
    "gn:feature_code":"PPL",
    "gn:name":"Riy\u0101mah",
    "gn:population":0,
    "gn:timezone":"Asia/Dubai",
    "iso:country":"AE",
    "name:und_x_variant":[
        "Riy\u0101mah",
        "Riyama"
    ],
    "wof:name":"Riyamah",
    "wof:placetype":"locality"
},
  "geometry": {"coordinates":[56.05836,25.54564],"type":"Point"}
}