{
  "type": "Feature",
  "properties": {
    "gn:admin1_code":"06",
    "gn:asciiname":"Qidfa`",
    "gn:country_code":"AE",
    "gn:dem":0,
    "gn:feature_class":"P",
    "gn:feature_code":"PPL",
    "gn:name":"Qidfa\u2018",
    "gn:population":0,
    "gn:timezone":"Asia/Dubai",
    "iso:country":"AE",
    "name:und_x_variant":[
        "Qidfi\u2018",
        "Qidfa\u2018",
        "Qidfa"
    ],
    "wof:name":"Qidfa`",
    "wof:placetype":"locality"
},
  "geometry": {"coordinates":[56.37034,25.30426],"type":"Point"}
}