{
  "type": "Feature",
  "properties": {
    "gn:admin1_code":"05",
    "gn:asciiname":"Khawr Khuwayr",
    "gn:country_code":"AE",
    "gn:dem":5,
    "gn:feature_class":"P",
    "gn:feature_code":"PPL",
    "gn:name":"Khawr Khuwayr",
    "gn:population":0,
    "gn:timezone":"Asia/Dubai",
    "iso:country":"AE",
    "name:und_x_variant":[
        "Khuwair",
        "Khor Khuwair",
        "Khawr Khuwayr"
    ],
    "wof:name":"Khawr Khuwayr",
    "wof:placetype":"locality"
},
  "geometry": {"coordinates":[56.05471,25.96577000000001],"type":"Point"}
}