{
  "type": "Feature",
  "properties": {
    "gn:admin1_code":"06",
    "gn:asciiname":"Ar Rufaysah",
    "gn:country_code":"AE",
    "gn:dem":81,
    "gn:feature_class":"P",
    "gn:feature_code":"PPL",
    "gn:name":"Ar Rufay\u015fah",
    "gn:population":0,
    "gn:timezone":"Asia/Dubai",
    "iso:country":"AE",
    "name:ara_x_preferred":[
        "\u0627\u0644\u0631\u0641\u064a\u0635\u0629"
    ],
    "name:und_x_variant":[
        "Ar Rufay\u015fah"
    ],
    "wof:name":"Ar Rufaysah",
    "wof:placetype":"locality"
},
  "geometry": {"coordinates":[56.3225,25.34518],"type":"Point"}
}