{
  "type": "Feature",
  "properties": {
    "iso:country":"AE",
    "name:ara_x_preferred":[
        "\u0647\u0648\u0631 \u0627\u0644\u0639\u0646\u0632"
    ],
    "name:eng_x_preferred":[
        "Hor Al Anz"
    ],
    "name:eng_x_variant":[
        "Hor Al Anz"
    ],
    "name:und_x_variant":[
        "Hawr al \u2018Anz"
    ],
    "qs:gn_adm0_cc":"AE",
    "qs:gn_fcode":"PPLX",
    "qs:gn_local":292223,
    "qs:gn_nam_loc":"\u062f\u0628\u064a, \u062f\u0628\u064a, \u062f\u0628\u064a, AE",
    "qs:gn_namadm1":"03",
    "qs:gn_name":"Hawr al \u2018Anz",
    "qs:local_max":8833,
    "qs:local_sum":49480,
    "qs:localhoods":73,
    "qs:name":"\u0647\u0648\u0631 \u0627\u0644\u0639\u0646\u0632",
    "qs:name_adm0":"\u0627\u0644\u0627\u0645\u0627\u0631\u0627\u062a",
    "qs:name_adm1":"\u062f\u0628\u064a",
    "qs:name_adm2":"\u062f\u0628\u064a",
    "qs:name_en":"Hor Al Anz",
    "qs:name_local":"\u062f\u0628\u064a",
    "qs:photo_max":14,
    "qs:photo_sum":19,
    "qs:placetype":"Suburb",
    "qs:quad_count":5,
    "qs:woe_adm0":23424738,
    "qs:woe_adm1":2347111,
    "qs:woe_adm2":55922623,
    "qs:woe_lau":0,
    "qs:woe_local":1940345,
    "qs:woe_ver":"7.10.0",
    "wof:name":"\u0647\u0648\u0631 \u0627\u0644\u0639\u0646\u0632",
    "wof:placetype":"neighbourhood"
},
  "geometry": {"coordinates":[55.338821,25.280092],"type":"Point"}
}