{
  "type": "Feature",
  "properties": {
    "gn:admin1_code":"05",
    "gn:asciiname":"Wahlah",
    "gn:country_code":"AE",
    "gn:dem":78,
    "gn:feature_class":"P",
    "gn:feature_code":"PPL",
    "gn:name":"Wa\u1e29lah",
    "gn:population":0,
    "gn:timezone":"Asia/Dubai",
    "iso:country":"AE",
    "name:ara_x_preferred":[
        "\u0648\u062d\u0644\u0629"
    ],
    "name:und_x_variant":[
        "Wahala",
        "Wa\u1e29lah"
    ],
    "wof:name":"Wahlah",
    "wof:placetype":"locality"
},
  "geometry": {"coordinates":[56.30316,24.90897],"type":"Point"}
}