{
  "type": "Feature",
  "properties": {
    "gn:admin1_code":"05",
    "gn:asciiname":"Masah",
    "gn:country_code":"AE",
    "gn:dem":462,
    "gn:feature_class":"P",
    "gn:feature_code":"PPL",
    "gn:name":"M\u0101sah",
    "gn:population":0,
    "gn:timezone":"Asia/Dubai",
    "iso:country":"AE",
    "name:ara_x_preferred":[
        "\u0627\u0644\u0645\u0633\u062d \u0639\u0644\u0649 \u0627\u0644\u062e\u0641\u064a\u0646"
    ],
    "name:bak_x_preferred":[
        "\u041c\u04d9\u0441\u0435\u0445"
    ],
    "name:deu_x_preferred":[
        "Al-Mash \u02bfal\u0101 l-chuffain"
    ],
    "name:rus_x_preferred":[
        "\u041c\u0430\u0441\u0445"
    ],
    "name:sqi_x_preferred":[
        "Mes'h"
    ],
    "name:und_x_variant":[
        "M\u0101sah"
    ],
    "wof:name":"Masah",
    "wof:placetype":"locality"
},
  "geometry": {"coordinates":[56.1649,25.30319],"type":"Point"}
}