{
  "type": "Feature",
  "properties": {
    "gn:admin1_code":"05",
    "gn:asciiname":"Masah",
    "gn:country_code":"AE",
    "gn:dem":462,
    "gn:feature_class":"P",
    "gn:feature_code":"PPL",
    "gn:name":"M\u0101sah",
    "gn:population":0,
    "gn:timezone":"Asia/Dubai",
    "iso:country":"AE",
    "name:ara_x_preferred":[
        "\u0645\u0627\u0633\u0629"
    ],
    "name:und_x_variant":[
        "M\u0101sah"
    ],
    "wof:name":"Masah",
    "wof:placetype":"locality"
},
  "geometry": {"coordinates":[56.1649,25.30319],"type":"Point"}
}