{
  "type": "Feature",
  "properties": {
    "gn:admin1_code":"05",
    "gn:asciiname":"Al Hamraniyah",
    "gn:country_code":"AE",
    "gn:dem":24,
    "gn:feature_class":"P",
    "gn:feature_code":"PPL",
    "gn:name":"Al \u1e28amr\u0101n\u012byah",
    "gn:population":0,
    "gn:timezone":"Asia/Dubai",
    "iso:country":"AE",
    "name:fas_x_preferred":[
        "\u0627\u0644\u0647\u0645\u0631\u0627\u0646\u06cc\u0647"
    ],
    "name:nno_x_preferred":[
        "Al Hamraniyah"
    ],
    "name:pnb_x_preferred":[
        "\u0627\u0644\u062d\u0645\u0631\u0627\u0646\u06cc\u06c1"
    ],
    "name:und_x_variant":[
        "Al \u1e28amr\u0101n\u012byah"
    ],
    "wof:name":"Al Hamraniyah",
    "wof:placetype":"neighbourhood"
},
  "geometry": {"coordinates":[55.90028,25.61139],"type":"Point"}
}