{
  "type": "Feature",
  "properties": {
    "gn:admin1_code":"05",
    "gn:asciiname":"Mawrid",
    "gn:country_code":"AE",
    "gn:dem":341,
    "gn:feature_class":"P",
    "gn:feature_code":"PPL",
    "gn:name":"Mawrid",
    "gn:population":0,
    "gn:timezone":"Asia/Dubai",
    "iso:country":"AE",
    "wof:name":"Mawrid",
    "wof:placetype":"locality"
},
  "geometry": {"coordinates":[56.11456999999999,25.42871],"type":"Point"}
}