{
  "type": "Feature",
  "properties": {
    "gn:admin1_code":"05",
    "gn:asciiname":"Mawrid",
    "gn:country_code":"AE",
    "gn:dem":341,
    "gn:feature_class":"P",
    "gn:feature_code":"PPL",
    "gn:name":"Mawrid",
    "gn:population":0,
    "gn:timezone":"Asia/Dubai",
    "iso:country":"AE",
    "name:ara_x_preferred":[
        "\u0645\u0648\u0631\u062f"
    ],
    "name:nno_x_preferred":[
        "Mawrid"
    ],
    "wof:name":"Mawrid",
    "wof:placetype":"locality"
},
  "geometry": {"coordinates":[56.11457,25.42871],"type":"Point"}
}