{
  "type": "Feature",
  "properties": {
    "gn:admin1_code":"01",
    "gn:asciiname":"Al Mughayra'",
    "gn:country_code":"AE",
    "gn:dem":13,
    "gn:feature_class":"P",
    "gn:feature_code":"PPL",
    "gn:name":"Al Mughayr\u0101\u2019",
    "gn:population":0,
    "gn:timezone":"Asia/Dubai",
    "iso:country":"AE",
    "name:und_x_variant":[
        "Mughaira",
        "Mugharah",
        "Mughairah",
        "Mughayrah",
        "Al Mughayr\u0101\u2019"
    ],
    "wof:name":"Al Mughayra'",
    "wof:placetype":"locality"
},
  "geometry": {"coordinates":[53.53842,24.07843],"type":"Point"}
}