{
  "type": "Feature",
  "properties": {
    "gn:admin1_code":"04",
    "gn:asciiname":"Yalah",
    "gn:country_code":"AE",
    "gn:dem":474,
    "gn:feature_class":"P",
    "gn:feature_code":"PPL",
    "gn:name":"Yalah",
    "gn:population":0,
    "gn:timezone":"Asia/Dubai",
    "iso:country":"AE",
    "name:ara_x_preferred":[
        "\u064a\u0627\u0644\u0627"
    ],
    "wof:name":"Yalah",
    "wof:placetype":"locality"
},
  "geometry": {"coordinates":[56.15496,25.41517],"type":"Point"}
}