{
  "type": "Feature",
  "properties": {
    "gn:admin1_code":"04",
    "gn:asciiname":"Dahir",
    "gn:country_code":"AE",
    "gn:dem":222,
    "gn:feature_class":"P",
    "gn:feature_code":"PPL",
    "gn:name":"\u1e10\u0101hir",
    "gn:population":0,
    "gn:timezone":"Asia/Dubai",
    "iso:country":"AE",
    "name:ara_x_preferred":[
        "\u0638\u0647\u064a\u0631"
    ],
    "name:ara_x_variant":[
        "\u1e10\u0101hir"
    ],
    "wof:name":"Dahir",
    "wof:placetype":"locality"
},
  "geometry": {"coordinates":[56.15499,25.53342],"type":"Point"}
}