{
  "type": "Feature",
  "properties": {
    "iso:country":"AE",
    "name:ara_x_preferred":[
        "\u0627\u0644\u0628\u0633\u062a\u0627\u0646"
    ],
    "name:eng_x_preferred":[
        "Al Bustan"
    ],
    "qs:gn_country":"AE",
    "qs:gn_fcode":"PPLX",
    "qs:gn_pop":0,
    "qs:name":"\u0627\u0644\u0628\u0633\u062a\u0627\u0646",
    "qs:name_adm0":"\u0627\u0644\u0627\u0645\u0627\u0631\u0627\u062a",
    "qs:name_adm1":"\u0627\u0644\u0634\u0627\u0631\u0642\u0629",
    "qs:photos":16,
    "qs:photos_1k":3,
    "qs:photos_9k":1,
    "qs:photos_9r":1,
    "qs:photos_all":16,
    "qs:photos_sr":1,
    "qs:placetype":"Suburb",
    "qs:pop_sr":"0",
    "qs:woe_adm0":23424738,
    "wof:lang_x_official":[
        "ara"
    ],
    "wof:lang_x_spoken":[
        "ara"
    ],
    "wof:name":"Al Bustan",
    "wof:placetype":"neighbourhood"
},
  "geometry": {"coordinates":[55.44577,25.41041],"type":"Point"}
}