{
  "type": "Feature",
  "properties": {
    "iso:country":"AE",
    "name:deu_x_preferred":[
        "Rams"
    ],
    "name:jpn_x_preferred":[
        "RAMS"
    ],
    "name:rus_x_preferred":[
        "\u0420\u0430\u043c\u0441"
    ],
    "qs:gn_pop":0,
    "qs:name":"Rams",
    "qs:name_adm0":"\u0627\u0644\u0627\u0645\u0627\u0631\u0627\u062a",
    "qs:name_adm1":"\u0631\u0627\u0633 \u0627\u0644\u062e\u064a\u0645\u0629",
    "qs:photos":66,
    "qs:photos_1k":13,
    "qs:photos_9k":1,
    "qs:photos_9r":2,
    "qs:photos_all":66,
    "qs:photos_sr":2,
    "qs:placetype":"Town",
    "qs:pop_sr":"0",
    "qs:woe_adm0":23424738,
    "wd:wordcount":280,
    "wof:name":"Rams",
    "wof:placetype":"neighbourhood"
},
  "geometry": {"coordinates":[56.0186,25.859655],"type":"Point"}
}