{
  "type": "Feature",
  "properties": {
    "gn:admin1_code":"01",
    "gn:asciiname":"Al Khabb",
    "gn:country_code":"AE",
    "gn:dem":294,
    "gn:feature_class":"P",
    "gn:feature_code":"PPL",
    "gn:name":"Al Khabb",
    "gn:population":0,
    "gn:timezone":"Asia/Dubai",
    "iso:country":"AE",
    "name:ara_x_preferred":[
        "\u0627\u0644\u062e\u0628"
    ],
    "wof:name":"Al Khabb",
    "wof:placetype":"locality"
},
  "geometry": {"coordinates":[55.74627,24.58969],"type":"Point"}
}