{
  "type": "Feature",
  "properties": {
    "iso:country":"AE",
    "qs:gn_pop":0,
    "qs:name":"\u0627\u0644\u0645\u0631\u0648\u062c 1",
    "qs:name_adm0":"\u0627\u0644\u0627\u0645\u0627\u0631\u0627\u062a",
    "qs:name_adm1":"\u062f\u0628\u064a",
    "qs:photos":61,
    "qs:photos_1k":12,
    "qs:photos_9k":1,
    "qs:photos_9r":2,
    "qs:photos_all":61,
    "qs:photos_sr":2,
    "qs:placetype":"Suburb",
    "qs:pop_sr":"0",
    "qs:woe_adm0":23424738,
    "wof:name":"\u0627\u0644\u0645\u0631\u0648\u062c 1",
    "wof:placetype":"neighbourhood"
},
  "geometry": {"coordinates":[55.149661,25.077442],"type":"Point"}
}