{
  "type": "Feature",
  "properties": {
    "iso:country":"AE",
    "name:ara_x_preferred":[
        "\u0627\u0644\u0628\u0627\u0647\u064a\u0629"
    ],
    "name:eng_x_preferred":[
        "Al Bahyah"
    ],
    "qs:gn_pop":0,
    "qs:name":"\u0627\u0644\u0628\u0627\u0647\u064a\u0629",
    "qs:name_adm0":"\u0627\u0644\u0627\u0645\u0627\u0631\u0627\u062a",
    "qs:name_adm1":"\u0623\u0628\u0648\u0638\u0628\u064a",
    "qs:photos":728,
    "qs:photos_1k":148,
    "qs:photos_9k":3,
    "qs:photos_9r":5,
    "qs:photos_all":728,
    "qs:photos_sr":8,
    "qs:placetype":"Town",
    "qs:pop_sr":"0",
    "qs:woe_adm0":23424738,
    "wof:name":"Al Bahyah",
    "wof:placetype":"neighbourhood"
},
  "geometry": {"coordinates":[54.607114,24.483301],"type":"Point"}
}