{
  "type": "Feature",
  "properties": {
    "gn:admin1_code":"01",
    "gn:asciiname":"Ghurbah",
    "gn:country_code":"AE",
    "gn:dem":5,
    "gn:feature_class":"P",
    "gn:feature_code":"PPL",
    "gn:name":"Ghurbah",
    "gn:population":0,
    "gn:timezone":"Asia/Dubai",
    "iso:country":"AE",
    "wof:name":"Ghurbah",
    "wof:placetype":"locality"
},
  "geometry": {"coordinates":[53.27171,24.28738],"type":"Point"}
}