{
  "type": "Feature",
  "properties": {
    "gn:admin1_code":"06",
    "gn:asciiname":"`Uqayr",
    "gn:country_code":"AE",
    "gn:dem":13,
    "gn:feature_class":"P",
    "gn:feature_code":"PPL",
    "gn:name":"\u2018Uqayr",
    "gn:population":0,
    "gn:timezone":"Asia/Dubai",
    "iso:country":"AE",
    "name:und_x_variant":[
        "\u2018Uqayr"
    ],
    "wof:lang_x_official":[
        "ara"
    ],
    "wof:lang_x_spoken":[
        "ara"
    ],
    "wof:name":"`Uqayr",
    "wof:placetype":"locality"
},
  "geometry": {"coordinates":[56.36435,25.28302],"type":"Point"}
}