{
  "type": "Feature",
  "properties": {
    "gn:admin1_code":"05",
    "gn:asciiname":"Darah",
    "gn:country_code":"AE",
    "gn:dem":380,
    "gn:feature_class":"P",
    "gn:feature_code":"PPL",
    "gn:name":"D\u0101rah",
    "gn:population":0,
    "gn:timezone":"Asia/Dubai",
    "iso:country":"AE",
    "name:und_x_variant":[
        "D\u0101rah"
    ],
    "wof:name":"Darah",
    "wof:placetype":"locality"
},
  "geometry": {"coordinates":[56.05722,25.10083],"type":"Point"}
}