{
  "type": "Feature",
  "properties": {
    "gn:admin1_code":"05",
    "gn:asciiname":"Suhaybah",
    "gn:country_code":"AE",
    "gn:dem":243,
    "gn:feature_class":"P",
    "gn:feature_code":"PPL",
    "gn:name":"Su\u1e29aybah",
    "gn:population":0,
    "gn:timezone":"Asia/Dubai",
    "iso:country":"AE",
    "name:und_x_variant":[
        "Su\u1e29aybah"
    ],
    "wof:name":"Suhaybah",
    "wof:placetype":"locality"
},
  "geometry": {"coordinates":[56.15754,24.93877],"type":"Point"}
}