{
  "type": "Feature",
  "properties": {
    "iso:country":"AE",
    "qs:gn_pop":0,
    "qs:name":"Umm Nahad",
    "qs:name_adm0":"\u0627\u0644\u0627\u0645\u0627\u0631\u0627\u062a",
    "qs:name_adm1":"\u062f\u0628\u064a",
    "qs:photos":178,
    "qs:photos_1k":36,
    "qs:photos_9k":1,
    "qs:photos_9r":4,
    "qs:photos_all":178,
    "qs:photos_sr":4,
    "qs:placetype":"Town",
    "qs:pop_sr":"0",
    "qs:woe_adm0":23424738,
    "wof:name":"Umm Nahad",
    "wof:placetype":"locality"
},
  "geometry": {"coordinates":[55.467267,25.0066335],"type":"Point"}
}