{
  "type": "Feature",
  "properties": {
    "iso:country":"AE",
    "name:ara_x_preferred":[
        "\u0627\u0644\u0634\u0647\u0627\u0645\u0629 \u0627\u0644\u062c\u062f\u064a\u062f\u0629"
    ],
    "name:eng_x_preferred":[
        "Al Shahama Al Jadeeda"
    ],
    "qs:gn_pop":0,
    "qs:name":"\u0627\u0644\u0634\u0647\u0627\u0645\u0629 \u0627\u0644\u062c\u062f\u064a\u062f\u0629",
    "qs:name_adm0":"\u0627\u0644\u0627\u0645\u0627\u0631\u0627\u062a",
    "qs:name_adm1":"\u0623\u0628\u0648\u0638\u0628\u064a",
    "qs:photos":132,
    "qs:photos_1k":27,
    "qs:photos_9k":1,
    "qs:photos_9r":3,
    "qs:photos_all":132,
    "qs:photos_sr":3,
    "qs:placetype":"County",
    "qs:pop_sr":"0",
    "qs:woe_adm0":23424738,
    "wof:name":"Al Shahama Al Jadeeda",
    "wof:placetype":"neighbourhood"
},
  "geometry": {"coordinates":[54.686809,24.554814],"type":"Point"}
}