{
  "type": "Feature",
  "properties": {
    "gn:admin1_code":"01",
    "gn:asciiname":"Al Mashrub",
    "gn:country_code":"AE",
    "gn:dem":102,
    "gn:feature_class":"P",
    "gn:feature_code":"PPL",
    "gn:name":"Al Mashr\u016bb",
    "gn:population":0,
    "gn:timezone":"Asia/Dubai",
    "iso:country":"AE",
    "name:ara_x_preferred":[
        "\u0627\u0644\u0645\u0634\u0631\u0628"
    ],
    "name:und_x_variant":[
        "Mashr\u016bb",
        "Mushayrib",
        "Al Mashr\u016bb"
    ],
    "wof:name":"Al Mashrub",
    "wof:placetype":"locality"
},
  "geometry": {"coordinates":[54.01347,23.07646],"type":"Point"}
}