{
  "type": "Feature",
  "properties": {
    "iso:country":"AE",
    "name:und_x_variant":[
        "Sharam"
    ],
    "qs:gn_country":"AE",
    "qs:gn_fcode":"PPL",
    "qs:gn_pop":0,
    "qs:name":"\u0634\u0631\u0645",
    "qs:name_adm0":"\u0627\u0644\u0627\u0645\u0627\u0631\u0627\u062a",
    "qs:name_adm1":"\u0627\u0644\u0641\u062c\u064a\u0631\u0629",
    "qs:photos":300,
    "qs:photos_1k":61,
    "qs:photos_9k":1,
    "qs:photos_9r":4,
    "qs:photos_all":300,
    "qs:photos_sr":5,
    "qs:placetype":"Town",
    "qs:pop_sr":"0",
    "qs:woe_adm0":23424738,
    "wof:lang_x_official":[
        "ara"
    ],
    "wof:lang_x_spoken":[
        "ara"
    ],
    "wof:name":"\u0634\u0631\u0645",
    "wof:placetype":"locality"
},
  "geometry": {"coordinates":[56.35319,25.47078],"type":"Point"}
}