{
  "type": "Feature",
  "properties": {
    "gn:admin1_code":"05",
    "gn:asciiname":"Shimal",
    "gn:country_code":"AE",
    "gn:dem":8,
    "gn:feature_class":"P",
    "gn:feature_code":"PPL",
    "gn:name":"Shim\u0101l",
    "gn:population":0,
    "gn:timezone":"Asia/Dubai",
    "iso:country":"AE",
    "name:ara_x_preferred":[
        "Shim\u0101l"
    ],
    "name:nno_x_preferred":[
        "Shimal"
    ],
    "name:und_x_variant":[
        "Shimil"
    ],
    "wof:lang_x_official":[
        "ara"
    ],
    "wof:lang_x_spoken":[
        "ara"
    ],
    "wof:name":"Shimal",
    "wof:placetype":"neighbourhood"
},
  "geometry": {"coordinates":[56.01088000000001,25.8178],"type":"Point"}
}