{
  "type": "Feature",
  "properties": {
    "iso:country":"AE",
    "name:ara_x_preferred":[
        "Al \u1e28i\u015fn"
    ],
    "name:ara_x_variant":[
        "\u0627\u0644\u062d\u0635\u0646"
    ],
    "qs:gn_country":"AE",
    "qs:gn_fcode":"PPLX",
    "qs:gn_pop":0,
    "qs:name":"\u0627\u0644\u062d\u0635\u0646",
    "qs:name_adm0":"\u0627\u0644\u0627\u0645\u0627\u0631\u0627\u062a",
    "qs:name_adm1":"\u0623\u0628\u0648\u0638\u0628\u064a",
    "qs:photos":87,
    "qs:photos_1k":18,
    "qs:photos_9k":1,
    "qs:photos_9r":3,
    "qs:photos_all":87,
    "qs:photos_sr":3,
    "qs:placetype":"Suburb",
    "qs:pop_sr":"0",
    "qs:woe_adm0":23424738,
    "wof:name":"\u0627\u0644\u062d\u0635\u0646",
    "wof:placetype":"neighbourhood"
},
  "geometry": {"coordinates":[54.35301,24.48023],"type":"Point"}
}