{
  "type": "Feature",
  "properties": {
    "gn:admin1_code":"06",
    "gn:asciiname":"Al `Awdah",
    "gn:country_code":"AE",
    "gn:dem":108,
    "gn:feature_class":"P",
    "gn:feature_code":"PPL",
    "gn:name":"Al \u2018Awdah",
    "gn:population":0,
    "gn:timezone":"Asia/Dubai",
    "iso:country":"AE",
    "name:und_x_variant":[
        "Al \u2018Awdah"
    ],
    "wof:name":"Al `Awdah",
    "wof:placetype":"locality"
},
  "geometry": {"coordinates":[56.30921,25.38068],"type":"Point"}
}