{
  "type": "Feature",
  "properties": {
    "iso:country":"AE",
    "qs:gn_country":"AE",
    "qs:gn_fcode":"PPL",
    "qs:gn_pop":0,
    "qs:name":"Mazyad",
    "qs:name_adm0":"\u0627\u0644\u0627\u0645\u0627\u0631\u0627\u062a",
    "qs:name_adm1":"\u0623\u0628\u0648\u0638\u0628\u064a",
    "qs:photos":211,
    "qs:photos_1k":43,
    "qs:photos_9k":1,
    "qs:photos_9r":4,
    "qs:photos_all":225,
    "qs:photos_sr":4,
    "qs:placetype":"Town",
    "qs:pop_sr":"0",
    "qs:woe_adm0":23424738,
    "wof:lang_x_official":[
        "ara"
    ],
    "wof:lang_x_spoken":[
        "ara"
    ],
    "wof:name":"Mazyad",
    "wof:placetype":"neighbourhood"
},
  "geometry": {"coordinates":[55.8425,24.03694],"type":"Point"}
}