{
  "type": "Feature",
  "properties": {
    "gn:admin1_code":"05",
    "gn:asciiname":"Salihiyah",
    "gn:country_code":"AE",
    "gn:dem":6,
    "gn:feature_class":"P",
    "gn:feature_code":"PPL",
    "gn:name":"\u015e\u0101li\u1e29\u012byah",
    "gn:population":0,
    "gn:timezone":"Asia/Dubai",
    "iso:country":"AE",
    "name:eng_x_preferred":[
        "Salihiyah"
    ],
    "name:und_x_variant":[
        "A\u015f \u015e\u0101li\u1e29\u012byah",
        "\u015e\u0101li\u1e29\u012byah"
    ],
    "wof:name":"Salihiyah",
    "wof:placetype":"neighbourhood"
},
  "geometry": {"coordinates":[55.99081,25.72161],"type":"Point"}
}