{
  "type": "Feature",
  "properties": {
    "gn:admin1_code":"01",
    "gn:asciiname":"Mujib",
    "gn:country_code":"AE",
    "gn:dem":166,
    "gn:feature_class":"P",
    "gn:feature_code":"PPL",
    "gn:name":"M\u016bjib",
    "gn:population":0,
    "gn:timezone":"Asia/Dubai",
    "iso:country":"AE",
    "name:ara_x_preferred":[
        "M\u016bjib"
    ],
    "wof:name":"Mujib",
    "wof:placetype":"locality"
},
  "geometry": {"coordinates":[53.68333000000001,23.11667000000001],"type":"Point"}
}