{
  "type": "Feature",
  "properties": {
    "gn:admin1_code":"01",
    "gn:asciiname":"Bu Lifiyat",
    "gn:country_code":"AE",
    "gn:dem":3,
    "gn:feature_class":"P",
    "gn:feature_code":"PPL",
    "gn:name":"B\u016b L\u012bf\u012by\u0101t",
    "gn:population":0,
    "gn:timezone":"Asia/Dubai",
    "iso:country":"AE",
    "name:ara_x_preferred":[
        "B\u016b L\u012bf\u012by\u0101t"
    ],
    "wof:name":"Bu Lifiyat",
    "wof:placetype":"locality"
},
  "geometry": {"coordinates":[53.81667,24.23333],"type":"Point"}
}