{
  "type": "Feature",
  "properties": {
    "gn:admin1_code":"03",
    "gn:asciiname":"Margham",
    "gn:country_code":"AE",
    "gn:dem":166,
    "gn:feature_class":"P",
    "gn:feature_code":"PPL",
    "gn:name":"Margham",
    "gn:population":0,
    "gn:timezone":"Asia/Dubai",
    "iso:country":"AE",
    "name:ara_x_preferred":[
        "\u0645\u0631\u063a\u0645"
    ],
    "wof:name":"Margham",
    "wof:placetype":"locality"
},
  "geometry": {"coordinates":[55.62402,24.89868],"type":"Point"}
}