{
  "type": "Feature",
  "properties": {
    "gn:admin1_code":"05",
    "gn:asciiname":"Al Ghashban",
    "gn:country_code":"AE",
    "gn:dem":105,
    "gn:feature_class":"P",
    "gn:feature_code":"PPL",
    "gn:name":"Al Ghashb\u0101n",
    "gn:population":0,
    "gn:timezone":"Asia/Dubai",
    "iso:country":"AE",
    "name:ara_x_preferred":[
        "\u0627\u0644\u063a\u0634\u0628\u0627\u0646"
    ],
    "name:und_x_variant":[
        "Al Ghashb\u0101n"
    ],
    "wof:name":"Al Ghashban",
    "wof:placetype":"locality"
},
  "geometry": {"coordinates":[56.11861,26.0425],"type":"Point"}
}