{
  "type": "Feature",
  "properties": {
    "gn:admin1_code":"06",
    "gn:asciiname":"Shis",
    "gn:country_code":"AE",
    "gn:dem":422,
    "gn:feature_class":"P",
    "gn:feature_code":"PPL",
    "gn:name":"Sh\u012bs",
    "gn:population":0,
    "gn:timezone":"Asia/Dubai",
    "iso:country":"AE",
    "name:ara_x_preferred":[
        "Sh\u012bs"
    ],
    "name:ara_x_variant":[
        "\u0634\u064a\u0635"
    ],
    "name:nno_x_preferred":[
        "Shis"
    ],
    "wof:name":"Shis",
    "wof:placetype":"locality"
},
  "geometry": {"coordinates":[56.24549,25.29138],"type":"Point"}
}