{
  "type": "Feature",
  "properties": {
    "gn:admin1_code":"04",
    "gn:asciiname":"Bulaydah",
    "gn:country_code":"AE",
    "gn:dem":264,
    "gn:feature_class":"P",
    "gn:feature_code":"PPL",
    "gn:name":"Bulaydah",
    "gn:population":0,
    "gn:timezone":"Asia/Dubai",
    "iso:country":"AE",
    "name:ara_x_preferred":[
        "\u0628\u0644\u064a\u062f\u0629"
    ],
    "name:und_x_variant":[
        "Bilaidah",
        "Bilaida",
        "Bulaydah",
        "Bulaidha"
    ],
    "wof:name":"Bulaydah",
    "wof:placetype":"locality"
},
  "geometry": {"coordinates":[56.20221,25.22388],"type":"Point"}
}