{
  "type": "Feature",
  "properties": {
    "gn:admin1_code":"05",
    "gn:asciiname":"Al Jazirah al Hamra'",
    "gn:country_code":"AE",
    "gn:dem":3,
    "gn:feature_class":"P",
    "gn:feature_code":"PPL",
    "gn:name":"Al Jaz\u012brah al \u1e28amr\u0101\u2019",
    "gn:population":0,
    "gn:timezone":"Asia/Dubai",
    "iso:country":"AE",
    "name:und_x_variant":[
        "Hamra",
        "Al \u1e28amr\u0101\u2019",
        "Al Jaz\u012brah al \u1e28amr\u0101\u2019"
    ],
    "wof:name":"Al Jazirah al Hamra'",
    "wof:placetype":"locality"
},
  "geometry": {"coordinates":[55.80772,25.7091],"type":"Point"}
}